wq/create/__init__.py
wq/create/forms.py
wq/create/projects.py
wq/create/version.py
wq/create/django_project/.gitignore
wq/create/django_project/README.md
wq/create/django_project/deploy.bat
wq/create/django_project/deploy.sh
wq/create/django_project/runserver.sh
wq/create/django_project/version.txt
wq/create/django_project/wq.yml
wq/create/django_project/app/README.md
wq/create/django_project/app/css/project_name.css
wq/create/django_project/app/images/icon-1024.png
wq/create/django_project/app/images/icon.svg
wq/create/django_project/app/js/project_name.js
wq/create/django_project/app/js/data/.gitignore
wq/create/django_project/app/public/favicon.ico
wq/create/django_project/app/public/index.html
wq/create/django_project/app/public/manifest.json
wq/create/django_project/conf/project_name.conf
wq/create/django_project/db/manage.py
wq/create/django_project/db/project_name/__init__.py
wq/create/django_project/db/project_name/asgi.py
wq/create/django_project/db/project_name/urls.py
wq/create/django_project/db/project_name/wsgi.py
wq/create/django_project/db/project_name/settings/.gitignore
wq/create/django_project/db/project_name/settings/__init__.py
wq/create/django_project/db/project_name/settings/base.py
wq/create/django_project/db/project_name/settings/dev.py
wq/create/django_project/db/project_name/settings/prod.py
wq/create/django_project/db/project_name_survey/__init__.py
wq/create/django_project/db/project_name_survey/models.py
wq/create/django_project/db/project_name_survey/rest.py
wq/create/django_project/db/project_name_survey/serializers.py
wq/create/django_project/db/project_name_survey/migrations/0001_initial.py
wq/create/django_project/db/project_name_survey/migrations/__init__.py
wq/create/django_project/media/.gitignore
wq.create-2.1.0.dist-info/LICENSE
wq.create-2.1.0.dist-info/METADATA
wq.create-2.1.0.dist-info/WHEEL
wq.create-2.1.0.dist-info/entry_points.txt
wq.create-2.1.0.dist-info/top_level.txt
wq.create-2.1.0.dist-info/RECORD
