Metadata-Version: 2.1
Name: wq.create
Version: 2.1.0
Summary: Project scaffolding tools for creating a new application with the wq framework.
Author-email: "S. Andrew Sheppard" <andrew@wq.io>
License: MIT
Project-URL: Homepage, https://wq.io/wq.create/
Project-URL: Documentation, https://wq.io/
Project-URL: Source, https://github.com/wq/wq.create
Project-URL: Release Notes, https://github.com/wq/wq.create/releases
Project-URL: Issues, https://github.com/wq/wq.create/issues
Project-URL: CI, https://github.com/wq/wq.create/actions/workflows/test.yml
Classifier: Development Status :: 5 - Production/Stable
Classifier: Environment :: Web Environment
Classifier: License :: OSI Approved :: MIT License
Classifier: Natural Language :: English
Classifier: Programming Language :: JavaScript
Classifier: Programming Language :: Python :: 3
Classifier: Programming Language :: Python :: 3.8
Classifier: Programming Language :: Python :: 3.9
Classifier: Programming Language :: Python :: 3.10
Classifier: Programming Language :: Python :: 3.11
Classifier: Programming Language :: Python :: 3.12
Classifier: Framework :: Django
Classifier: Framework :: Django :: 4.0
Classifier: Framework :: Django :: 4.1
Classifier: Framework :: Django :: 4.2
Classifier: Framework :: Django :: 5.0
Classifier: Topic :: Software Development :: Libraries :: Application Frameworks
Classifier: Topic :: Software Development :: Code Generators
Classifier: Topic :: Text Processing :: Markup :: HTML
Classifier: Topic :: Software Development :: Build Tools
Classifier: Topic :: Software Development :: Pre-processors
Requires-Python: >=3.8
License-File: LICENSE
Requires-Dist: wq.build >=2.1.0
Requires-Dist: xlsconv <2.2.0,>=2.0.0
Requires-Dist: psycopg2-binary
